cycls/__init__.py
cycls/app.py
cycls/auth.py
cycls/cli.py
cycls/function.py
cycls/state.py
cycls/web.py
cycls/themes/default/index.html
cycls/themes/default/assets/FileSaver.min-BN40akLc.js
cycls/themes/default/assets/html2canvas.esm-QH1iLAAe.js
cycls/themes/default/assets/index-3AQCbjkB.js
cycls/themes/default/assets/index-CjN0qc53.css
cycls/themes/default/assets/index-qcHL6SRo.js
cycls/themes/default/assets/index.es-BmxgotDY.js
cycls/themes/default/assets/jspdf.es.min-CvOy4co6.js
cycls/themes/default/assets/purify.es-B9ZVCkUG.js
cycls/themes/dev/index.html
cycls-0.0.2.102.dist-info/METADATA
cycls-0.0.2.102.dist-info/WHEEL
cycls-0.0.2.102.dist-info/entry_points.txt
cycls-0.0.2.102.dist-info/RECORD
