Metadata-Version: 2.4
Name: cycls
Version: 0.0.2.102
Summary: Distribute Intelligence
Author-email: "Mohammed J. AlRujayi" <mj@cycls.com>
Requires-Python: >=3.10
Requires-Dist: cloudpickle>=3.1.1
Requires-Dist: docker>=7.1.0
Requires-Dist: email-validator>=2.0.0
Requires-Dist: fastapi>=0.111.0
Requires-Dist: httpx>=0.27.0
Requires-Dist: pyjwt>=2.8.0
Requires-Dist: uvicorn>=0.30.0
Requires-Dist: watchfiles>=1.0.0
Provides-Extra: state
Requires-Dist: agentfs-sdk==0.4.0; extra == 'state'
